hvvapi/__init__.py
hvvapi/hvv_client.py
hvvapi-0.1.0.dist-info/METADATA
hvvapi-0.1.0.dist-info/WHEEL
hvvapi-0.1.0.dist-info/licenses/LICENSE
hvvapi-0.1.0.dist-info/RECORD
