Metadata-Version: 2.4
Name: hvvapi
Version: 0.1.0
Summary: Simple Python client for the HVV Geofox GTI API
Project-URL: Homepage, https://github.com/jaronkramer/hvvapi
Project-URL: Repository, https://github.com/jaronkramer/hvvapi
Author-email: Jaron Kramer <info@jkramertech.com>
License: MIT
License-File: LICENSE
Keywords: api,geofox,hamburg,hvv,public-transport
Classifier: Development Status :: 3 - Alpha
Classifier: Intended Audience :: Developers
Classifier: License :: OSI Approved :: MIT License
Classifier: Programming Language :: Python :: 3
Classifier: Programming Language :: Python :: 3.12
Requires-Python: >=3.12
Requires-Dist: requests>=2.32.5
